Workbook

Sheet Summary
A1: Summary — เปรียบเทียบ 3 Scenario (Year 1)
A3: Metric | B3: Conservative | C3: Base | D3: Optimistic
A4: Pre-Launch Capital (ลงทุนแรก) | B4: =Assumptions!B11 -> 25000 | C4: =Assumptions!C11 -> 12000 | D4: =Assumptions!D11 -> 6000
A5: Max Cash Drawdown (เงินติดลบสูงสุด) | B5: =MIN(Conservative!B15:M15) -> -79325.22 | C5: =MIN(Base!B15:M15) -> -18194.12 | D5: =MIN(Optimistic!B15:M15) -> -1221.96
A6: Peak Paying Users | B6: =MAX(Conservative!B7:M7) -> 144 | C6: =MAX(Base!B7:M7) -> 400 | D6: =MAX(Optimistic!B7:M7) -> 1050
A7: Year-1 Gross Revenue | B7: =SUM(Conservative!B8:M8) -> 135579 | C7: =SUM(Base!B8:M8) -> 376164 | D7: =SUM(Optimistic!B8:M8) -> 987753
A8: Year-1 Net Revenue (หลัง fee) | B8: =SUM(Conservative!B9:M9) -> 111174.78 | C8: =SUM(Base!B9:M9) -> 346070.88 | D8: =SUM(Optimistic!B9:M9) -> 958120.41
A9: Year-1 Operating+Mktg Cost | B9: =SUM(Conservative!B13:M13) -> 165500 | C9: =SUM(Base!B13:M13) -> 135920 | D9: =SUM(Optimistic!B13:M13) -> 106752
A10: Year-1 Net Profit (หลัง Pre-Launch) | B10: =Conservative!M15 -> -79325.22 | C10: =Base!M15 -> 198150.88 | D10: =Optimistic!M15 -> 845368.41
A11: Net Margin % | B11: =IFERROR(Conservative!M15/SUM(Conservative!B8:M8),0) -> -0.58508486 | C11: =IFERROR(Base!M15/SUM(Base!B8:M8),0) -> 0.52676726 | D11: =IFERROR(Optimistic!M15/SUM(Optimistic!B8:M8),0) -> 0.85585001
A12: Peak Monthly Net Revenue | B12: =MAX(Conservative!B9:M9) -> 15232.32 | C12: =MAX(Base!B9:M9) -> 47472 | D12: =MAX(Optimistic!B9:M9) -> 131386.5
A13: Break-even (เดือนที่เงินสด > 0) | B13: =IFERROR(INDEX(Conservative!$B$3:$M$3,MATCH(1,INDEX(--(Conservative!$B$15:$M$15>0),0),0)),"ไม่คืนทุนในปี1") -> ไม่คืนทุนในปี1 | C13: =IFERROR(INDEX(Base!$B$3:$M$3,MATCH(1,INDEX(--(Base!$B$15:$M$15>0),0),0)),"ไม่คืนทุนในปี1") -> ธ.ค. | D13: =IFERROR(INDEX(Optimistic!$B$3:$M$3,MATCH(1,INDEX(--(Optimistic!$B$15:$M$15>0),0),0)),"ไม่คืนทุนในปี1") -> ต.ค.
A16: หมายเหตุ:
A17: • Base = สมมติฐานที่แนะนำให้ใช้วางแผนจริง (conversion 20%, organic CAC, reverse trial)
A18: • ปรับตัวเลขทั้งหมดได้ที่ชีต Assumptions (เซลล์สีน้ำเงิน) แล้วทุกชีตอัปเดตตาม
A19: • Pre-Launch Capital ลดมาก: seed bank gen ผ่าน Claude Code flat-rate (≈0) + verify มือ → เหลือแค่ infra/misc
A20: • ตัด free 2 เดือนทิ้ง → reverse trial เก็บเงินตั้งแต่เดือน 1 (Free Period = 0)
A21: • Claude Code subscription (fixed) อยู่ใน Monthly Operating Cost แล้ว ไม่ใช่ Pre-Launch
A22: • Max Cash Drawdown = เงินที่ต้องมีในกระเป๋าจริงก่อนถึงจุดคืนทุน
A23: • ตัวเลขนี้ยังไม่รวมเงินเดือน/ค่าเสียโอกาสของ solo founder

Sheet Assumptions
A1: TCAS AI Practice App — Financial Model (3 Scenarios)
A2: ทุกตัวเลขสีน้ำเงิน = ปรับได้ / สีดำ = สูตร / สีเขียว = ลิงก์ข้ามชีต | หน่วย: บาท (THB)
A4: Assumption | B4: Conservative | C4: Base (แนะนำ) | D4: Optimistic | E4: หน่วย / หมายเหตุ
A5: Peak Total Users (เดือน ม.ค.) | B5: 1200 | C5: 2000 | D5: 3000 | E5: คน — ยอดผู้ใช้สูงสุด (พีคฤดูสอบ)
A6: Conversion Rate (free→paid) | B6: 0.12 | C6: 0.2 | D6: 0.35 | E6: % ของ user ที่จ่ายเงิน
A7: ARPU (บาท/ผู้จ่าย/เดือน) | B7: 129 | C7: 129 | D7: 129 | E7: 99×0.8 + 249×0.2
A8: Transaction + Store Fee | B8: 0.18 | C8: 0.08 | D8: 0.03 | E8: % — payment gateway + app store cut
A9: CAC (บาท/ผู้ใช้ใหม่) | B9: 20 | C9: 10 | D9: 4 | E9: ต้นทุนหา user ใหม่ 1 คน — organic ช่วง launch (no paid mktg)
A10: Monthly Operating Cost | B10: 11000 | C10: 9000 | D10: 7500 | E10: บาท/เดือน — Claude Code sub (flat) + infra/hosting + gen/verify demand-driven
A11: Pre-Launch Capital | B11: 25000 | C11: 12000 | D11: 6000 | E11: บาท — infra setup + misc (seed bank gen ≈ 0 ผ่าน Claude Code + verify มือ)
A12: Free Period (เดือนแรกที่ไม่เก็บเงิน) | B12: 0 | C12: 0 | D12: 0 | E12: เดือน — reverse trial (trial สั้น → เก็บเงินตั้งแต่เดือน 1)
A14: Pre-Launch breakdown (Base ~12k):
A15: Seed bank ~4k โจทย์: gen ผ่าน Claude Code (flat subscription, marginal cost ≈ 0) + verify = พี่ตรวจมือเอง (0 API) | เหลือแค่ infra setup + domain + misc
A16: Claude Code subscription (~$100-200/mo) เป็น fixed cost ที่จ่ายอยู่แล้ว ไม่ scale ตาม bank → ย้ายไปอยู่ใน Monthly Operating Cost ไม่ใช่ Pre-Launch
A19: Seasonal Demand Curve (% ของพีค ม.ค.)
A20: เดือน | B20: ก.ย. | C20: ต.ค. | D20: พ.ย. | E20: ธ.ค. | F20: ม.ค. | G20: ก.พ. | H20: มี.ค. | I20: เม.ย. | J20: พ.ค. | K20: มิ.ย. | L20: ก.ค. | M20: ส.ค.
A21: % ของพีค | B21: 0.103 | C21: 0.276 | D21: 0.483 | E21: 0.724 | F21: 1 | G21: 0.828 | H21: 0.586 | I21: 0.483 | J21: 0.552 | K21: 0.638 | L21: 0.741 | M21: 0.879

Sheet Conservative
A1: Scenario: Conservative
A3: เดือน | B3: ก.ย. | C3: ต.ค. | D3: พ.ย. | E3: ธ.ค. | F3: ม.ค. | G3: ก.พ. | H3: มี.ค. | I3: เม.ย. | J3: พ.ค. | K3: มิ.ย. | L3: ก.ค. | M3: ส.ค.
A4: Season % of peak | B4: =Assumptions!B$21 -> 0.103 | C4: =Assumptions!C$21 -> 0.276 | D4: =Assumptions!D$21 -> 0.483 | E4: =Assumptions!E$21 -> 0.724 | F4: =Assumptions!F$21 -> 1 | G4: =Assumptions!G$21 -> 0.828 | H4: =Assumptions!H$21 -> 0.586 | I4: =Assumptions!I$21 -> 0.483 | ... M4: =Assumptions!M$21 -> 0.879
A5: Total Users | B5: =ROUND(Assumptions!$B$5*B4,0) -> 124 | C5: =ROUND(Assumptions!$B$5*C4,0) -> 331 | D5: =ROUND(Assumptions!$B$5*D4,0) -> 580 | E5: =ROUND(Assumptions!$B$5*E4,0) -> 869 | F5: =ROUND(Assumptions!$B$5*F4,0) -> 1200 | G5: =ROUND(Assumptions!$B$5*G4,0) -> 994 | H5: =ROUND(Assumptions!$B$5*H4,0) -> 703 | I5: =ROUND(Assumptions!$B$5*I4,0) -> 580 | ... M5: =ROUND(Assumptions!$B$5*M4,0) -> 1055
A6: Charging? (1=เก็บเงิน) | B6: =IF(COLUMN()-1>Assumptions!$B$12,1,0) -> 1 | C6: =IF(COLUMN()-1>Assumptions!$B$12,1,0) -> 1 | D6: =IF(COLUMN()-1>Assumptions!$B$12,1,0) -> 1 | E6: =IF(COLUMN()-1>Assumptions!$B$12,1,0) -> 1 | F6: =IF(COLUMN()-1>Assumptions!$B$12,1,0) -> 1 | G6: =IF(COLUMN()-1>Assumptions!$B$12,1,0) -> 1 | H6: =IF(COLUMN()-1>Assumptions!$B$12,1,0) -> 1 | I6: =IF(COLUMN()-1>Assumptions!$B$12,1,0) -> 1 | ... M6: =IF(COLUMN()-1>Assumptions!$B$12,1,0) -> 1
A7: Paying Users | B7: =ROUND(B5*Assumptions!$B$6*B6,0) -> 15 | C7: =ROUND(C5*Assumptions!$B$6*C6,0) -> 40 | D7: =ROUND(D5*Assumptions!$B$6*D6,0) -> 70 | E7: =ROUND(E5*Assumptions!$B$6*E6,0) -> 104 | F7: =ROUND(F5*Assumptions!$B$6*F6,0) -> 144 | G7: =ROUND(G5*Assumptions!$B$6*G6,0) -> 119 | H7: =ROUND(H5*Assumptions!$B$6*H6,0) -> 84 | I7: =ROUND(I5*Assumptions!$B$6*I6,0) -> 70 | ... M7: =ROUND(M5*Assumptions!$B$6*M6,0) -> 127
A8: Gross Revenue (บาท) | B8: =B7*Assumptions!$B$7 -> 1935 | C8: =C7*Assumptions!$B$7 -> 5160 | D8: =D7*Assumptions!$B$7 -> 9030 | E8: =E7*Assumptions!$B$7 -> 13416 | F8: =F7*Assumptions!$B$7 -> 18576 | G8: =G7*Assumptions!$B$7 -> 15351 | H8: =H7*Assumptions!$B$7 -> 10836 | I8: =I7*Assumptions!$B$7 -> 9030 | ... M8: =M7*Assumptions!$B$7 -> 16383
A9: Net Revenue (หลังค่าธรรมเนียม) | B9: =B8*(1-Assumptions!$B$8) -> 1586.7 | C9: =C8*(1-Assumptions!$B$8) -> 4231.2 | D9: =D8*(1-Assumptions!$B$8) -> 7404.6 | E9: =E8*(1-Assumptions!$B$8) -> 11001.12 | F9: =F8*(1-Assumptions!$B$8) -> 15232.32 | G9: =G8*(1-Assumptions!$B$8) -> 12587.82 | H9: =H8*(1-Assumptions!$B$8) -> 8885.52 | I9: =I8*(1-Assumptions!$B$8) -> 7404.6 | ... M9: =M8*(1-Assumptions!$B$8) -> 13434.06
A10: New Users (acquired) | B10: =B5 -> 124 | C10: =MAX(0,C5-B5) -> 207 | D10: =MAX(0,D5-C5) -> 249 | E10: =MAX(0,E5-D5) -> 289 | F10: =MAX(0,F5-E5) -> 331 | G10: =MAX(0,G5-F5) -> 0 | H10: =MAX(0,H5-G5) -> 0 | I10: =MAX(0,I5-H5) -> 0 | J10: =MAX(0,J5-I5) -> 82 | ... M10: =MAX(0,M5-L5) -> 166
A11: Marketing/CAC Cost | B11: =B10*Assumptions!$B$9 -> 2480 | C11: =C10*Assumptions!$B$9 -> 4140 | D11: =D10*Assumptions!$B$9 -> 4980 | E11: =E10*Assumptions!$B$9 -> 5780 | F11: =F10*Assumptions!$B$9 -> 6620 | G11: =G10*Assumptions!$B$9 -> 0 | H11: =H10*Assumptions!$B$9 -> 0 | I11: =I10*Assumptions!$B$9 -> 0 | ... M11: =M10*Assumptions!$B$9 -> 3320
A12: Operating Cost | B12: =Assumptions!$B$10 -> 11000 | C12: =Assumptions!$B$10 -> 11000 | D12: =Assumptions!$B$10 -> 11000 | E12: =Assumptions!$B$10 -> 11000 | F12: =Assumptions!$B$10 -> 11000 | G12: =Assumptions!$B$10 -> 11000 | H12: =Assumptions!$B$10 -> 11000 | I12: =Assumptions!$B$10 -> 11000 | ... M12: =Assumptions!$B$10 -> 11000
A13: Total Cost | B13: =B11+B12 -> 13480 | C13: =C11+C12 -> 15140 | D13: =D11+D12 -> 15980 | E13: =E11+E12 -> 16780 | F13: =F11+F12 -> 17620 | G13: =G11+G12 -> 11000 | H13: =H11+H12 -> 11000 | I13: =I11+I12 -> 11000 | ... M13: =M11+M12 -> 14320
A14: Net Profit / เดือน | B14: =B9-B13 -> -11893.3 | C14: =C9-C13 -> -10908.8 | D14: =D9-D13 -> -8575.4 | E14: =E9-E13 -> -5778.88 | F14: =F9-F13 -> -2387.68 | G14: =G9-G13 -> 1587.82 | H14: =H9-H13 -> -2114.48 | I14: =I9-I13 -> -3595.4 | ... M14: =M9-M13 -> -885.94
A15: Cumulative Cash (สะสม) | B15: =-Assumptions!$B$11+B14 -> -36893.3 | C15: =B15+C14 -> -47802.1 | D15: =C15+D14 -> -56377.5 | E15: =D15+E14 -> -62156.38 | F15: =E15+F14 -> -64544.06 | G15: =F15+G14 -> -62956.24 | H15: =G15+H14 -> -65070.72 | I15: =H15+I14 -> -68666.12 | J15: =I15+J14 -> -72949.5 | ... M15: =L15+M14 -> -79325.22
A17: เริ่มต้นด้วยเงินลงทุน Pre-Launch = | B17: =-Assumptions!$B$11 -> -25000

Sheet Base
A1: Scenario: Base
A3: เดือน | B3: ก.ย. | C3: ต.ค. | D3: พ.ย. | E3: ธ.ค. | F3: ม.ค. | G3: ก.พ. | H3: มี.ค. | I3: เม.ย. | J3: พ.ค. | K3: มิ.ย. | L3: ก.ค. | M3: ส.ค.
A4: Season % of peak | B4: =Assumptions!B$21 -> 0.103 | C4: =Assumptions!C$21 -> 0.276 | D4: =Assumptions!D$21 -> 0.483 | E4: =Assumptions!E$21 -> 0.724 | F4: =Assumptions!F$21 -> 1 | G4: =Assumptions!G$21 -> 0.828 | H4: =Assumptions!H$21 -> 0.586 | I4: =Assumptions!I$21 -> 0.483 | ... M4: =Assumptions!M$21 -> 0.879
A5: Total Users | B5: =ROUND(Assumptions!$C$5*B4,0) -> 206 | C5: =ROUND(Assumptions!$C$5*C4,0) -> 552 | D5: =ROUND(Assumptions!$C$5*D4,0) -> 966 | E5: =ROUND(Assumptions!$C$5*E4,0) -> 1448 | F5: =ROUND(Assumptions!$C$5*F4,0) -> 2000 | G5: =ROUND(Assumptions!$C$5*G4,0) -> 1656 | H5: =ROUND(Assumptions!$C$5*H4,0) -> 1172 | I5: =ROUND(Assumptions!$C$5*I4,0) -> 966 | ... M5: =ROUND(Assumptions!$C$5*M4,0) -> 1758
A6: Charging? (1=เก็บเงิน) | B6: =IF(COLUMN()-1>Assumptions!$C$12,1,0) -> 1 | C6: =IF(COLUMN()-1>Assumptions!$C$12,1,0) -> 1 | D6: =IF(COLUMN()-1>Assumptions!$C$12,1,0) -> 1 | E6: =IF(COLUMN()-1>Assumptions!$C$12,1,0) -> 1 | F6: =IF(COLUMN()-1>Assumptions!$C$12,1,0) -> 1 | G6: =IF(COLUMN()-1>Assumptions!$C$12,1,0) -> 1 | H6: =IF(COLUMN()-1>Assumptions!$C$12,1,0) -> 1 | I6: =IF(COLUMN()-1>Assumptions!$C$12,1,0) -> 1 | ... M6: =IF(COLUMN()-1>Assumptions!$C$12,1,0) -> 1
A7: Paying Users | B7: =ROUND(B5*Assumptions!$C$6*B6,0) -> 41 | C7: =ROUND(C5*Assumptions!$C$6*C6,0) -> 110 | D7: =ROUND(D5*Assumptions!$C$6*D6,0) -> 193 | E7: =ROUND(E5*Assumptions!$C$6*E6,0) -> 290 | F7: =ROUND(F5*Assumptions!$C$6*F6,0) -> 400 | G7: =ROUND(G5*Assumptions!$C$6*G6,0) -> 331 | H7: =ROUND(H5*Assumptions!$C$6*H6,0) -> 234 | I7: =ROUND(I5*Assumptions!$C$6*I6,0) -> 193 | ... M7: =ROUND(M5*Assumptions!$C$6*M6,0) -> 352
A8: Gross Revenue (บาท) | B8: =B7*Assumptions!$C$7 -> 5289 | C8: =C7*Assumptions!$C$7 -> 14190 | D8: =D7*Assumptions!$C$7 -> 24897 | E8: =E7*Assumptions!$C$7 -> 37410 | F8: =F7*Assumptions!$C$7 -> 51600 | G8: =G7*Assumptions!$C$7 -> 42699 | H8: =H7*Assumptions!$C$7 -> 30186 | I8: =I7*Assumptions!$C$7 -> 24897 | ... M8: =M7*Assumptions!$C$7 -> 45408
A9: Net Revenue (หลังค่าธรรมเนียม) | B9: =B8*(1-Assumptions!$C$8) -> 4865.88 | C9: =C8*(1-Assumptions!$C$8) -> 13054.8 | D9: =D8*(1-Assumptions!$C$8) -> 22905.24 | E9: =E8*(1-Assumptions!$C$8) -> 34417.2 | F9: =F8*(1-Assumptions!$C$8) -> 47472 | G9: =G8*(1-Assumptions!$C$8) -> 39283.08 | H9: =H8*(1-Assumptions!$C$8) -> 27771.12 | I9: =I8*(1-Assumptions!$C$8) -> 22905.24 | ... M9: =M8*(1-Assumptions!$C$8) -> 41775.36
A10: New Users (acquired) | B10: =B5 -> 206 | C10: =MAX(0,C5-B5) -> 346 | D10: =MAX(0,D5-C5) -> 414 | E10: =MAX(0,E5-D5) -> 482 | F10: =MAX(0,F5-E5) -> 552 | G10: =MAX(0,G5-F5) -> 0 | H10: =MAX(0,H5-G5) -> 0 | I10: =MAX(0,I5-H5) -> 0 | J10: =MAX(0,J5-I5) -> 138 | ... M10: =MAX(0,M5-L5) -> 276
A11: Marketing/CAC Cost | B11: =B10*Assumptions!$C$9 -> 2060 | C11: =C10*Assumptions!$C$9 -> 3460 | D11: =D10*Assumptions!$C$9 -> 4140 | E11: =E10*Assumptions!$C$9 -> 4820 | F11: =F10*Assumptions!$C$9 -> 5520 | G11: =G10*Assumptions!$C$9 -> 0 | H11: =H10*Assumptions!$C$9 -> 0 | I11: =I10*Assumptions!$C$9 -> 0 | ... M11: =M10*Assumptions!$C$9 -> 2760
A12: Operating Cost | B12: =Assumptions!$C$10 -> 9000 | C12: =Assumptions!$C$10 -> 9000 | D12: =Assumptions!$C$10 -> 9000 | E12: =Assumptions!$C$10 -> 9000 | F12: =Assumptions!$C$10 -> 9000 | G12: =Assumptions!$C$10 -> 9000 | H12: =Assumptions!$C$10 -> 9000 | I12: =Assumptions!$C$10 -> 9000 | ... M12: =Assumptions!$C$10 -> 9000
A13: Total Cost | B13: =B11+B12 -> 11060 | C13: =C11+C12 -> 12460 | D13: =D11+D12 -> 13140 | E13: =E11+E12 -> 13820 | F13: =F11+F12 -> 14520 | G13: =G11+G12 -> 9000 | H13: =H11+H12 -> 9000 | I13: =I11+I12 -> 9000 | ... M13: =M11+M12 -> 11760
A14: Net Profit / เดือน | B14: =B9-B13 -> -6194.12 | C14: =C9-C13 -> 594.8 | D14: =D9-D13 -> 9765.24 | E14: =E9-E13 -> 20597.2 | F14: =F9-F13 -> 32952 | G14: =G9-G13 -> 30283.08 | H14: =H9-H13 -> 18771.12 | I14: =I9-I13 -> 13905.24 | ... M14: =M9-M13 -> 30015.36
A15: Cumulative Cash (สะสม) | B15: =-Assumptions!$C$11+B14 -> -18194.12 | C15: =B15+C14 -> -17599.32 | D15: =C15+D14 -> -7834.08 | E15: =D15+E14 -> 12763.12 | F15: =E15+F14 -> 45715.12 | G15: =F15+G14 -> 75998.2 | H15: =G15+H14 -> 94769.32 | I15: =H15+I14 -> 108674.56 | J15: =I15+J14 -> 124522.84 | ... M15: =L15+M14 -> 198150.88
A17: เริ่มต้นด้วยเงินลงทุน Pre-Launch = | B17: =-Assumptions!$C$11 -> -12000

Sheet Optimistic
A1: Scenario: Optimistic
A3: เดือน | B3: ก.ย. | C3: ต.ค. | D3: พ.ย. | E3: ธ.ค. | F3: ม.ค. | G3: ก.พ. | H3: มี.ค. | I3: เม.ย. | J3: พ.ค. | K3: มิ.ย. | L3: ก.ค. | M3: ส.ค.
A4: Season % of peak | B4: =Assumptions!B$21 -> 0.103 | C4: =Assumptions!C$21 -> 0.276 | D4: =Assumptions!D$21 -> 0.483 | E4: =Assumptions!E$21 -> 0.724 | F4: =Assumptions!F$21 -> 1 | G4: =Assumptions!G$21 -> 0.828 | H4: =Assumptions!H$21 -> 0.586 | I4: =Assumptions!I$21 -> 0.483 | ... M4: =Assumptions!M$21 -> 0.879
A5: Total Users | B5: =ROUND(Assumptions!$D$5*B4,0) -> 309 | C5: =ROUND(Assumptions!$D$5*C4,0) -> 828 | D5: =ROUND(Assumptions!$D$5*D4,0) -> 1449 | E5: =ROUND(Assumptions!$D$5*E4,0) -> 2172 | F5: =ROUND(Assumptions!$D$5*F4,0) -> 3000 | G5: =ROUND(Assumptions!$D$5*G4,0) -> 2484 | H5: =ROUND(Assumptions!$D$5*H4,0) -> 1758 | I5: =ROUND(Assumptions!$D$5*I4,0) -> 1449 | ... M5: =ROUND(Assumptions!$D$5*M4,0) -> 2637
A6: Charging? (1=เก็บเงิน) | B6: =IF(COLUMN()-1>Assumptions!$D$12,1,0) -> 1 | C6: =IF(COLUMN()-1>Assumptions!$D$12,1,0) -> 1 | D6: =IF(COLUMN()-1>Assumptions!$D$12,1,0) -> 1 | E6: =IF(COLUMN()-1>Assumptions!$D$12,1,0) -> 1 | F6: =IF(COLUMN()-1>Assumptions!$D$12,1,0) -> 1 | G6: =IF(COLUMN()-1>Assumptions!$D$12,1,0) -> 1 | H6: =IF(COLUMN()-1>Assumptions!$D$12,1,0) -> 1 | I6: =IF(COLUMN()-1>Assumptions!$D$12,1,0) -> 1 | ... M6: =IF(COLUMN()-1>Assumptions!$D$12,1,0) -> 1
A7: Paying Users | B7: =ROUND(B5*Assumptions!$D$6*B6,0) -> 108 | C7: =ROUND(C5*Assumptions!$D$6*C6,0) -> 290 | D7: =ROUND(D5*Assumptions!$D$6*D6,0) -> 507 | E7: =ROUND(E5*Assumptions!$D$6*E6,0) -> 760 | F7: =ROUND(F5*Assumptions!$D$6*F6,0) -> 1050 | G7: =ROUND(G5*Assumptions!$D$6*G6,0) -> 869 | H7: =ROUND(H5*Assumptions!$D$6*H6,0) -> 615 | I7: =ROUND(I5*Assumptions!$D$6*I6,0) -> 507 | ... M7: =ROUND(M5*Assumptions!$D$6*M6,0) -> 923
A8: Gross Revenue (บาท) | B8: =B7*Assumptions!$D$7 -> 13932 | C8: =C7*Assumptions!$D$7 -> 37410 | D8: =D7*Assumptions!$D$7 -> 65403 | E8: =E7*Assumptions!$D$7 -> 98040 | F8: =F7*Assumptions!$D$7 -> 135450 | G8: =G7*Assumptions!$D$7 -> 112101 | H8: =H7*Assumptions!$D$7 -> 79335 | I8: =I7*Assumptions!$D$7 -> 65403 | ... M8: =M7*Assumptions!$D$7 -> 119067
A9: Net Revenue (หลังค่าธรรมเนียม) | B9: =B8*(1-Assumptions!$D$8) -> 13514.04 | C9: =C8*(1-Assumptions!$D$8) -> 36287.7 | D9: =D8*(1-Assumptions!$D$8) -> 63440.91 | E9: =E8*(1-Assumptions!$D$8) -> 95098.8 | F9: =F8*(1-Assumptions!$D$8) -> 131386.5 | G9: =G8*(1-Assumptions!$D$8) -> 108737.97 | H9: =H8*(1-Assumptions!$D$8) -> 76954.95 | I9: =I8*(1-Assumptions!$D$8) -> 63440.91 | ... M9: =M8*(1-Assumptions!$D$8) -> 115494.99
A10: New Users (acquired) | B10: =B5 -> 309 | C10: =MAX(0,C5-B5) -> 519 | D10: =MAX(0,D5-C5) -> 621 | E10: =MAX(0,E5-D5) -> 723 | F10: =MAX(0,F5-E5) -> 828 | G10: =MAX(0,G5-F5) -> 0 | H10: =MAX(0,H5-G5) -> 0 | I10: =MAX(0,I5-H5) -> 0 | J10: =MAX(0,J5-I5) -> 207 | ... M10: =MAX(0,M5-L5) -> 414
A11: Marketing/CAC Cost | B11: =B10*Assumptions!$D$9 -> 1236 | C11: =C10*Assumptions!$D$9 -> 2076 | D11: =D10*Assumptions!$D$9 -> 2484 | E11: =E10*Assumptions!$D$9 -> 2892 | F11: =F10*Assumptions!$D$9 -> 3312 | G11: =G10*Assumptions!$D$9 -> 0 | H11: =H10*Assumptions!$D$9 -> 0 | I11: =I10*Assumptions!$D$9 -> 0 | ... M11: =M10*Assumptions!$D$9 -> 1656
A12: Operating Cost | B12: =Assumptions!$D$10 -> 7500 | C12: =Assumptions!$D$10 -> 7500 | D12: =Assumptions!$D$10 -> 7500 | E12: =Assumptions!$D$10 -> 7500 | F12: =Assumptions!$D$10 -> 7500 | G12: =Assumptions!$D$10 -> 7500 | H12: =Assumptions!$D$10 -> 7500 | I12: =Assumptions!$D$10 -> 7500 | ... M12: =Assumptions!$D$10 -> 7500
A13: Total Cost | B13: =B11+B12 -> 8736 | C13: =C11+C12 -> 9576 | D13: =D11+D12 -> 9984 | E13: =E11+E12 -> 10392 | F13: =F11+F12 -> 10812 | G13: =G11+G12 -> 7500 | H13: =H11+H12 -> 7500 | I13: =I11+I12 -> 7500 | ... M13: =M11+M12 -> 9156
A14: Net Profit / เดือน | B14: =B9-B13 -> 4778.04 | C14: =C9-C13 -> 26711.7 | D14: =D9-D13 -> 53456.91 | E14: =E9-E13 -> 84706.8 | F14: =F9-F13 -> 120574.5 | G14: =G9-G13 -> 101237.97 | H14: =H9-H13 -> 69454.95 | I14: =I9-I13 -> 55940.91 | ... M14: =M9-M13 -> 106338.99
A15: Cumulative Cash (สะสม) | B15: =-Assumptions!$D$11+B14 -> -1221.96 | C15: =B15+C14 -> 25489.74 | D15: =C15+D14 -> 78946.65 | E15: =D15+E14 -> 163653.45 | F15: =E15+F14 -> 284227.95 | G15: =F15+G14 -> 385465.92 | H15: =G15+H14 -> 454920.87 | I15: =H15+I14 -> 510861.78 | J15: =I15+J14 -> 575109.18 | ... M15: =L15+M14 -> 845368.41
A17: เริ่มต้นด้วยเงินลงทุน Pre-Launch = | B17: =-Assumptions!$D$11 -> -6000
